Moodipy/LoadPage.py
Moodipy/MoodAnalyzerGUI.py
Moodipy/PlaylistGUI.py
Moodipy/PlaylistGenerator.py
Moodipy/SpotifyAuthorization.py
Moodipy/Spotipy.py
Moodipy/UserLogin.py
Moodipy/UserSummary.py
Moodipy/__init__.py
Moodipy/emotions.txt
Moodipy/main.py
Moodipy/moodAnalyzer.py
Moodipy/moodTrendsPg.py
Moodipy/imgs/arrow.png
Moodipy/imgs/awful.jpeg
Moodipy/imgs/bad.jpeg
Moodipy/imgs/excited.jpeg
Moodipy/imgs/happy.jpeg
Moodipy/imgs/love.jpeg
Moodipy/imgs/okay.jpeg
Moodipy-0.115.dist-info/LICENSE
Moodipy-0.115.dist-info/METADATA
Moodipy-0.115.dist-info/WHEEL
Moodipy-0.115.dist-info/entry_points.txt
Moodipy-0.115.dist-info/top_level.txt
Moodipy-0.115.dist-info/RECORD
